frogpy/__init__.py
frogpy/algebra/__init__.py
frogpy/algebra/matrix.py
frogpy/algebra/tools.py
frogpy-1.0.2.dist-info/LICENSE
frogpy-1.0.2.dist-info/METADATA
frogpy-1.0.2.dist-info/WHEEL
frogpy-1.0.2.dist-info/top_level.txt
frogpy-1.0.2.dist-info/RECORD
